README.rst
setup.py
dj_blog.egg-info/PKG-INFO
dj_blog.egg-info/SOURCES.txt
dj_blog.egg-info/dependency_links.txt
dj_blog.egg-info/not-zip-safe
dj_blog.egg-info/requires.txt
dj_blog.egg-info/top_level.txt
djblog/__init__.py
djblog/admin.py
djblog/mixins.py
djblog/models.py
djblog/sitemaps.py
djblog/urls.py
djblog/utils.py
djblog/views.py
djblog/migrations/0001_initial.py
djblog/migrations/__init__.py
tests/__init__.py
tests/test_mixins.py
tests/test_models.py
tests/test_sitemaps.py
tests/test_views.py
tests/urls.py