Metadata-Version: 1.1
Name: dj-blog
Version: 0.3.1
Summary: a very basic blog app for a django project
Home-page: https://github.com/buddylindsey/dj-blog
Author: Buddy Lindsey, Jr.
Author-email: buddy@buddylindsey.com
License: BSD
Keywords: django blog
Platform: UNKNOWN
Classifier: Development Status :: 3 - Alpha
Classifier: Environment :: Web Environment
Classifier: Framework :: Django
Classifier: Intended Audience :: Developers
Classifier: License :: OSI Approved :: BSD License
Classifier: Natural Language :: English
Classifier: Programming Language :: Python :: 2
Classifier: Programming Language :: Python :: 2.6
Classifier: Programming Language :: Python :: 2.7
